setup.cfg
setup.py
django_fastcgi/__init__.py
django_fastcgi.egg-info/PKG-INFO
django_fastcgi.egg-info/SOURCES.txt
django_fastcgi.egg-info/dependency_links.txt
django_fastcgi.egg-info/not-zip-safe
django_fastcgi.egg-info/requires.txt
django_fastcgi.egg-info/top_level.txt
django_fastcgi/management/__init__.py
django_fastcgi/management/models.py
django_fastcgi/management/commands/__init__.py
django_fastcgi/management/commands/run_fcgi.py