Metadata-Version: 1.0
Name: django-fastcgi
Version: 0.0.1
Summary: Exposes a management command to connect to FastCGI server
Home-page: UNKNOWN
Author: UNKNOWN
Author-email: UNKNOWN
License: UNKNOWN
Platform: UNKNOWN
